{
    "description": "A template for Horizon Project-Air service",
    "documentation": "https://github.com/TIBCOSoftware/labs-air/integration/oh/README.md",
    "sharable": "multiple",
    "org": "myorg",
    "label": "edgex.1.2 for amd64",
    "url": "edgex.1.2",
    "version": "0.1.0",
    "arch": "amd64",
    "requiredServices": [],
    "deployment": {
        "services": {
            "edgex-core-consul": {
                "image": "edgexfoundry/docker-edgex-consul:1.2.0",
                "privileged": true,
                "network": "host",
                "environment": [
                    "EDGEX_DB=localhost",
                    "EDGEX_SECURE=False",
                    "CONSUL_CLIENT_INTERFACE=$CONSUL_CLIENT_INTERFACE",
                    "CONSUL_BIND_INTERFACE=$CONSUL_BIND_INTERFACE"
                ],
                "binds": [
                    "consul-config:/consul/config:z",
                    "consul-data:/consul/data:z"
                ],
                "entrypoint": [],
                "devices": []
            },
            "edgex-redis": {
                "image": "redis:5.0.8-alpine",
                "privileged": true,
                "network": "host",
                "environment": [
                    "EDGEX_SECURITY_SECRET_STORE=false",
                    "Registry_Host=localhost",
                    "Clients_CoreData_Host=localhost",
                    "Clients_Data_Host=localhost",
                    "Clients_Notifications_Host=localhost",
                    "Clients_Metadata_Host=localhost",
                    "Clients_Command_Host=localhost",
                    "Clients_Scheduler_Host=localhost",
                    "Clients_RulesEngine_Host=localhost",
                    "Clients_VirtualDevice_Host=localhost",
                    "Databases_Primary_Host=localhost",
                    "Logging_EnableRemote=false"
                ],
                "binds": [
                    "db-data:/data:z"
                ],
                "entrypoint": [],
                "devices": []
            },
            "edgex-support-notifications": {
                "image": "edgexfoundry/docker-support-notifications-go:1.2.1",
                "privileged": true,
                "network": "host",
                "environment": [
                    "EDGEX_SECURITY_SECRET_STORE=false",
                    "Registry_Host=localhost",
                    "Clients_CoreData_Host=localhost",
                    "Clients_Data_Host=localhost",
                    "Clients_Notifications_Host=localhost",
                    "Clients_Metadata_Host=localhost",
                    "Clients_Command_Host=localhost",
                    "Clients_Scheduler_Host=localhost",
                    "Clients_RulesEngine_Host=localhost",
                    "Clients_VirtualDevice_Host=localhost",
                    "Databases_Primary_Host=localhost",
                    "Logging_EnableRemote=false",
                    "Service_Host=localhost"
                ],
                "binds": [],
                "entrypoint": [
                    "/support-notifications",
                    "-cp=consul.http://localhost:8500",
                    "--confdir=/res",
                    "--registry"
                ],
                "devices": []
            },
            "edgex-core-metadata": {
                "image": "edgexfoundry/docker-core-metadata-go:1.2.1",
                "privileged": true,
                "network": "host",
                "environment": [
                    "EDGEX_SECURITY_SECRET_STORE=false",
                    "Registry_Host=localhost",
                    "Clients_CoreData_Host=localhost",
                    "Clients_Data_Host=localhost",
                    "Clients_Notifications_Host=localhost",
                    "Clients_Metadata_Host=localhost",
                    "Clients_Command_Host=localhost",
                    "Clients_Scheduler_Host=localhost",
                    "Clients_RulesEngine_Host=localhost",
                    "Clients_VirtualDevice_Host=localhost",
                    "Databases_Primary_Host=localhost",
                    "Logging_EnableRemote=false",
                    "Service_Host=localhost",
                    "Service_Timeout=20000",
                    "Notifications_Sender=localhost"
                ],
                "binds": [],
                "entrypoint": [
                    "/core-metadata",
                    "-cp=consul.http://localhost:8500",
                    "--confdir=/res",
                    "--registry"
                ],
                "devices": []
            },
            "edgex-core-data": {
                "image": "edgexfoundry/docker-core-data-go:1.2.1",
                "privileged": true,
                "network": "host",
                "environment": [
                    "EDGEX_SECURITY_SECRET_STORE=false",
                    "Registry_Host=localhost",
                    "Clients_CoreData_Host=localhost",
                    "Clients_Data_Host=localhost",
                    "Clients_Notifications_Host=localhost",
                    "Clients_Metadata_Host=localhost",
                    "Clients_Command_Host=localhost",
                    "Clients_Scheduler_Host=localhost",
                    "Clients_RulesEngine_Host=localhost",
                    "Clients_VirtualDevice_Host=localhost",
                    "Databases_Primary_Host=localhost",
                    "Logging_EnableRemote=false",
                    "Service_Host=localhost"
                ],
                "binds": [],
                "entrypoint": [
                    "/core-data",
                    "-cp=consul.http://localhost:8500",
                    "--confdir=/res",
                    "--registry"
                ],
                "devices": []
            },
            "edgex-core-command": {
                "image": "edgexfoundry/docker-core-command-go:1.2.1",
                "privileged": true,
                "network": "host",
                "environment": [
                    "EDGEX_SECURITY_SECRET_STORE=false",
                    "Registry_Host=localhost",
                    "Clients_CoreData_Host=localhost",
                    "Clients_Data_Host=localhost",
                    "Clients_Notifications_Host=localhost",
                    "Clients_Metadata_Host=localhost",
                    "Clients_Command_Host=localhost",
                    "Clients_Scheduler_Host=localhost",
                    "Clients_RulesEngine_Host=localhost",
                    "Clients_VirtualDevice_Host=localhost",
                    "Databases_Primary_Host=localhost",
                    "Logging_EnableRemote=false",
                    "Service_Host=localhost"
                ],
                "binds": [],
                "entrypoint": [
                    "/core-command",
                    "-cp=consul.http://localhost:8500",
                    "--confdir=/res",
                    "--registry"
                ],
                "devices": []
            },
            "edgex-support-scheduler": {
                "image": "edgexfoundry/docker-support-scheduler-go:1.2.1",
                "privileged": true,
                "network": "host",
                "environment": [
                    "EDGEX_SECURITY_SECRET_STORE=false",
                    "Registry_Host=localhost",
                    "Clients_CoreData_Host=localhost",
                    "Clients_Data_Host=localhost",
                    "Clients_Notifications_Host=localhost",
                    "Clients_Metadata_Host=localhost",
                    "Clients_Command_Host=localhost",
                    "Clients_Scheduler_Host=localhost",
                    "Clients_RulesEngine_Host=localhost",
                    "Clients_VirtualDevice_Host=localhost",
                    "Databases_Primary_Host=localhost",
                    "Logging_EnableRemote=false",
                    "Service_Host=localhost",
                    "IntervalActions_ScrubPushed_Host=localhost",
                    "IntervalActions_ScrubAged_Host=localhost"
                ],
                "binds": [],
                "entrypoint": [
                    "/support-scheduler",
                    "-cp=consul.http://localhost:8500",
                    "--confdir=/res",
                    "--registry"
                ],
                "devices": []
            },
            "mqtt": {
                "image": "eclipse-mosquitto:1.5.8",
                "privileged": true,
                "network": "host",
                "environment": [],
                "binds": [],
                "entrypoint": [],
                "devices": []
            },
            "edgex-device-rest": {
                "image": "edgexfoundry/docker-device-rest-go:1.1.1",
                "privileged": true,
                "network": "host",
                "environment": [
                    "EDGEX_SECURITY_SECRET_STORE=false",
                    "Registry_Host=localhost",
                    "Clients_CoreData_Host=localhost",
                    "Clients_Data_Host=localhost",
                    "Clients_Notifications_Host=localhost",
                    "Clients_Metadata_Host=localhost",
                    "Clients_Command_Host=localhost",
                    "Clients_Scheduler_Host=localhost",
                    "Clients_RulesEngine_Host=localhost",
                    "Clients_VirtualDevice_Host=localhost",
                    "Databases_Primary_Host=localhost",
                    "Logging_EnableRemote=false",
                    "Service_Host=localhost"
                ],
                "binds": [
                    "/home/ubuntu/loss-detection-app/res/device-rest-go/:/res/"
                ],
                "entrypoint": [
                    "/device-rest-go",
                    "-cp=consul.http://localhost:8500",
                    "--confdir=/res",
                    "--registry"
                ],
                "devices": []
            },
            "edgex-device-mqtt": {
                "image": "edgexfoundry/docker-device-mqtt-go:1.2.1",
                "privileged": true,
                "network": "host",
                "environment": [
                    "EDGEX_SECURITY_SECRET_STORE=false",
                    "Registry_Host=localhost",
                    "Clients_CoreData_Host=localhost",
                    "Clients_Data_Host=localhost",
                    "Clients_Notifications_Host=localhost",
                    "Clients_Metadata_Host=localhost",
                    "Clients_Command_Host=localhost",
                    "Clients_Scheduler_Host=localhost",
                    "Clients_RulesEngine_Host=localhost",
                    "Clients_VirtualDevice_Host=localhost",
                    "Databases_Primary_Host=localhost",
                    "Logging_EnableRemote=false",
                    "Service_Host=localhost",
                    "Driver_IncomingHost=localhost",
                    "Driver_ResponseHost=localhost",
                    "Driver_IncomingTopic=edgex/#",
                    "Driver_IncomingClientId=edgex-mqtt-sub",
                    "Driver_ResponseClientId=edgex-mqtt-command-sub",
                    "Driver_ResponseTopic=Edgex-command-response"
                ],
                "binds": [
                    "/home/ubuntu/loss-detection-app/res/device-mqtt-go/:/res/"
                ],
                "entrypoint": [
                    "/device-mqtt",
                    "-cp=consul.http://localhost:8500",
                    "--confdir=/res",
                    "--registry"
                ],
                "devices": []
            }
        }
    }
}